Metadata-Version: 2.1
Name: pururin
Version: 0.0.7
Summary: Pururin unofficial API
Home-page: https://github.com/sinkaroid/pururin
Author: sinkaroid
Author-email: anakmancasan@gmail.com
License: MIT
Keywords: pururin,doujin,wrapper
Platform: UNKNOWN
Classifier: Framework :: AsyncIO
Classifier: Development Status :: 3 - Alpha
Classifier: Intended Audience :: Developers
Classifier: License :: OSI Approved :: MIT License
Classifier: Natural Language :: English
Classifier: Operating System :: OS Independent
Classifier: Programming Language :: Python :: 3.7
Classifier: Programming Language :: Python :: 3.8
Classifier: Programming Language :: Python :: 3.9
Classifier: Programming Language :: Python :: 3.10
Classifier: Topic :: Internet :: WWW/HTTP
Classifier: Topic :: Software Development :: Libraries
Classifier: Topic :: Software Development :: Libraries :: Application Frameworks
Classifier: Topic :: Software Development :: Libraries :: Python Modules
